MANIFEST.in
requirements.txt
setup.cfg
setup.py
aws_conduit/__init__.py
aws_conduit/conduit.py
aws_conduit/conduit_factory.py
aws_conduit/conduit_portfolio.py
aws_conduit/conduit_product.py
aws_conduit/conduit_role.py
aws_conduit/conduit_s3.py
aws_conduit/conduit_start.py
aws_conduit/helper.py
aws_conduit.egg-info/PKG-INFO
aws_conduit.egg-info/SOURCES.txt
aws_conduit.egg-info/dependency_links.txt
aws_conduit.egg-info/entry_points.txt
aws_conduit.egg-info/requires.txt
aws_conduit.egg-info/top_level.txt
aws_conduit/aws/__init__.py
aws_conduit/aws/cloudformation.py
aws_conduit/aws/iam.py
aws_conduit/aws/s3.py
aws_conduit/aws/service_catalog.py
aws_conduit/aws/ssm.py