Metadata-Version: 1.1
Name: aws-conduit
Version: 0.0.30
Summary: Product management for AWS Service Catalog.
Home-page: https://github.com/concon121/aws-conduit
Author: Connor Bray
Author-email: connor.bray@icloud.com
License: UNKNOWN
Download-URL: https://github.com/concon121/aws-conduit/archive/0.0.30.tar.gz
Keywords: aws,servicecatalog
Platform: UNKNOWN
